diamond/__init__.py
diamond/distributed/__init__.py
diamond/distributed/client/__init__.py
diamond/distributed/client/client_manager.py
diamond/distributed/communication/__init__.py
diamond/distributed/communication/com_manager.py
diamond/distributed/communication/message.py
diamond/distributed/communication/mpi_message.py
diamond/distributed/communication/mpi_receive_thread.py
diamond/distributed/communication/mpi_send_thread.py
diamond/distributed/communication/observer.py
diamond/distributed/server/__init__.py
diamond/distributed/server/server_manager.py
diamond/distributed/topology/__init__.py
diamond/distributed/topology/topology_manager.py
ml_diamond-0.1.1.dist-info/LICENSE
ml_diamond-0.1.1.dist-info/METADATA
ml_diamond-0.1.1.dist-info/WHEEL
ml_diamond-0.1.1.dist-info/top_level.txt
ml_diamond-0.1.1.dist-info/RECORD
