Metadata-Version: 2.1
Name: ml-diamond
Version: 0.1.1
Summary: DIAMOND: A Flexible Distributed Machine Learning Library for Novel Learning Algorithms and Models
Home-page: https://github.com/chaoyanghe/diamond
Author: Chaoyang He
Author-email: me@chaoyanghe.com
License: UNKNOWN
Platform: UNKNOWN
Classifier: Programming Language :: Python :: 3
Classifier: License :: OSI Approved :: MIT License
Classifier: Operating System :: OS Independent
Requires-Python: >=3.6
